pyworxcloud/__init__.py
pyworxcloud/api.py
pyworxcloud/clouds.py
pyworxcloud/const.py
pyworxcloud/day_map.py
pyworxcloud/events.py
pyworxcloud/exceptions.py
pyworxcloud/helpers/__init__.py
pyworxcloud/helpers/logger.py
pyworxcloud/helpers/time_format.py
pyworxcloud/utils/__init__.py
pyworxcloud/utils/battery.py
pyworxcloud/utils/blades.py
pyworxcloud/utils/capability.py
pyworxcloud/utils/devices.py
pyworxcloud/utils/firmware.py
pyworxcloud/utils/landroid_class.py
pyworxcloud/utils/lawn.py
pyworxcloud/utils/location.py
pyworxcloud/utils/mqtt.py
pyworxcloud/utils/orientation.py
pyworxcloud/utils/product.py
pyworxcloud/utils/rainsensor.py
pyworxcloud/utils/requests.py
pyworxcloud/utils/schedules.py
pyworxcloud/utils/state.py
pyworxcloud/utils/statistics.py
pyworxcloud/utils/warranty.py
pyworxcloud/utils/zone.py
pyworxcloud-5.0.0.dist-info/LICENSE
pyworxcloud-5.0.0.dist-info/METADATA
pyworxcloud-5.0.0.dist-info/WHEEL
pyworxcloud-5.0.0.dist-info/RECORD
