Metadata-Version: 2.3
Name: pyworxcloud
Version: 5.0.0
Summary: Landroid cloud (Positec) API library
License: MIT
Author: Malene Trab
Author-email: malene@trab.dk
Requires-Python: >=3.9,<4.0
Classifier: License :: OSI Approved :: MIT License
Classifier: Programming Language :: Python :: 3
Classifier: Programming Language :: Python :: 3.9
Classifier: Programming Language :: Python :: 3.10
Classifier: Programming Language :: Python :: 3.11
Classifier: Programming Language :: Python :: 3.12
Classifier: Programming Language :: Python :: 3.13
Classifier: Topic :: Software Development :: Libraries :: Python Modules
Requires-Dist: awsiotsdk (==1.24.0)
Requires-Dist: requests (>=2.32.0,<3.0.0)
Requires-Dist: urllib3 (>=1.26.5)
Project-URL: Bug Tracker, https://github.com/mtrab/pyworxcloud/issues
Project-URL: Documentation, https://github.com/mtrab/pyworxcloud
